{
  "metadata": {
    "generated_at": "2025-07-02T11:52:51.745322",
    "location": "St. Louis, MO",
    "total_jobs": 8,
    "unique_companies": 8,
    "pipeline_stages": [
      "Data Collection",
      "Preprocessing",
      "Embedding Generation",
      "Job Matching"
    ]
  },
  "top_matches": [
    {
      "rank": 1,
      "job_title": "Software Engineerineerineer",
      "company_name": "Boeing",
      "location": "Saint Louis, MO",
      "salary_range": "80000 - 120000",
      "required_skills": "java, python, aerospace, real-time systems, embedded software",
      "similarity_score": 1.0,
      "job_url": "https://jobs.boeing.com/software-engineer"
    },
    {
      "rank": 2,
      "job_title": "Python Developer",
      "company_name": "Centene Corporation",
      "location": "Saint Louis, MO",
      "salary_range": "75000 - 110000",
      "required_skills": "python, django, postgresql, healthcare, hipaa",
      "similarity_score": 0.9999,
      "job_url": "https://careers.centene.com/python-developer"
    },
    {
      "rank": 3,
      "job_title": "Data Scientistentistentist",
      "company_name": "Express Scripts",
      "location": "Saint Louis, MO",
      "salary_range": "90000 - 130000",
      "required_skills": "machine learning, python, r, healthcare analytics, pharmaceutical",
      "similarity_score": 0.9997,
      "job_url": "https://careers.express-scripts.com/data-scientist"
    },
    {
      "rank": 4,
      "job_title": "Frontend Developer",
      "company_name": "World Wide Technology",
      "location": "Saint Louis, MO",
      "salary_range": "70000 - 100000",
      "required_skills": "react, javascript, typescript, css, responsive design, cloud, devops",
      "similarity_score": 0.9994,
      "job_url": "https://careers.wwt.com/frontend-developer"
    },
    {
      "rank": 5,
      "job_title": "Devops Engineer",
      "company_name": "Ameren",
      "location": "Saint Louis, MO",
      "salary_range": "85000 - 125000",
      "required_skills": "aws, docker, kubernetes, ci/cd, energy sector, compliance",
      "similarity_score": 0.9989,
      "job_url": "https://careers.ameren.com/devops-engineer"
    }
  ]
}